{
    "Initial_routing": [
        [
            314,
            455
        ],
        [
            455,
            316
        ],
        [
            316,
            322
        ],
        [
            322,
            321
        ],
        [
            321,
            324
        ],
        [
            324,
            430
        ],
        [
            430,
            341
        ],
        [
            341,
            429
        ],
        [
            429,
            450
        ],
        [
            450,
            434
        ],
        [
            434,
            393
        ],
        [
            393,
            449
        ],
        [
            449,
            463
        ],
        [
            463,
            377
        ],
        [
            377,
            379
        ],
        [
            379,
            392
        ],
        [
            392,
            338
        ]
    ],
    "Final_routing": [
        [
            314,
            455
        ],
        [
            455,
            313
        ],
        [
            313,
            362
        ],
        [
            362,
            447
        ],
        [
            447,
            328
        ],
        [
            328,
            454
        ],
        [
            454,
            442
        ],
        [
            442,
            440
        ],
        [
            440,
            360
        ],
        [
            360,
            330
        ],
        [
            330,
            326
        ],
        [
            326,
            329
        ],
        [
            329,
            453
        ],
        [
            453,
            451
        ],
        [
            451,
            365
        ],
        [
            365,
            450
        ],
        [
            450,
            429
        ],
        [
            429,
            428
        ],
        [
            428,
            385
        ],
        [
            385,
            436
        ],
        [
            436,
            374
        ],
        [
            374,
            437
        ],
        [
            437,
            375
        ],
        [
            375,
            383
        ],
        [
            383,
            463
        ],
        [
            463,
            420
        ],
        [
            420,
            423
        ],
        [
            423,
            422
        ],
        [
            422,
            418
        ],
        [
            418,
            392
        ],
        [
            392,
            338
        ]
    ],
    "Properties": {
        "Waypoint": {
            "startNode": 314,
            "finalNode": 338,
            "waypoint": 450
        },
        "LoopFreedom": {
            "startNode": 314
        },
        "Reachability": {
            "startNode": 314,
            "finalNode": 338
        }
    }
}