{
    "Initial_routing": [
        [
            196,
            189
        ],
        [
            189,
            190
        ],
        [
            190,
            191
        ],
        [
            191,
            192
        ],
        [
            192,
            180
        ],
        [
            180,
            204
        ],
        [
            204,
            193
        ],
        [
            193,
            205
        ],
        [
            205,
            198
        ],
        [
            198,
            206
        ],
        [
            206,
            403
        ],
        [
            403,
            396
        ],
        [
            396,
            397
        ],
        [
            397,
            398
        ],
        [
            398,
            399
        ],
        [
            399,
            387
        ],
        [
            387,
            411
        ],
        [
            411,
            400
        ],
        [
            400,
            412
        ],
        [
            412,
            405
        ],
        [
            405,
            413
        ],
        [
            413,
            610
        ],
        [
            610,
            603
        ],
        [
            603,
            604
        ],
        [
            604,
            605
        ],
        [
            605,
            606
        ],
        [
            606,
            594
        ],
        [
            594,
            618
        ],
        [
            618,
            607
        ],
        [
            607,
            619
        ],
        [
            619,
            612
        ],
        [
            612,
            620
        ],
        [
            620,
            817
        ],
        [
            817,
            810
        ],
        [
            810,
            811
        ],
        [
            811,
            812
        ],
        [
            812,
            813
        ],
        [
            813,
            801
        ],
        [
            801,
            825
        ],
        [
            825,
            814
        ],
        [
            814,
            826
        ],
        [
            826,
            819
        ],
        [
            819,
            827
        ]
    ],
    "Final_routing": [
        [
            196,
            195
        ],
        [
            195,
            188
        ],
        [
            188,
            187
        ],
        [
            187,
            184
        ],
        [
            184,
            183
        ],
        [
            183,
            186
        ],
        [
            186,
            185
        ],
        [
            185,
            181
        ],
        [
            181,
            198
        ],
        [
            198,
            206
        ],
        [
            206,
            403
        ],
        [
            403,
            402
        ],
        [
            402,
            395
        ],
        [
            395,
            394
        ],
        [
            394,
            391
        ],
        [
            391,
            390
        ],
        [
            390,
            393
        ],
        [
            393,
            392
        ],
        [
            392,
            388
        ],
        [
            388,
            405
        ],
        [
            405,
            413
        ],
        [
            413,
            610
        ],
        [
            610,
            609
        ],
        [
            609,
            602
        ],
        [
            602,
            601
        ],
        [
            601,
            598
        ],
        [
            598,
            597
        ],
        [
            597,
            600
        ],
        [
            600,
            599
        ],
        [
            599,
            595
        ],
        [
            595,
            612
        ],
        [
            612,
            620
        ],
        [
            620,
            817
        ],
        [
            817,
            816
        ],
        [
            816,
            809
        ],
        [
            809,
            808
        ],
        [
            808,
            805
        ],
        [
            805,
            804
        ],
        [
            804,
            807
        ],
        [
            807,
            806
        ],
        [
            806,
            802
        ],
        [
            802,
            819
        ],
        [
            819,
            827
        ]
    ],
    "Properties": {
        "Waypoint": {
            "startNode": 196,
            "finalNode": 827,
            "waypoint": 610
        },
        "LoopFreedom": {
            "startNode": 196
        },
        "Reachability": {
            "startNode": 196,
            "finalNode": 827
        }
    }
}